gittask/__init__.py
gittask/asana_client.py
gittask/config.py
gittask/database.py
gittask/git_handler.py
gittask/main.py
gittask/utils.py
gittask/commands/auth.py
gittask/commands/checkout.py
gittask/commands/commit.py
gittask/commands/finish.py
gittask/commands/init.py
gittask/commands/pr.py
gittask/commands/push.py
gittask/commands/session.py
gittask/commands/status.py
gittask/commands/sync.py
gittask/commands/tags.py
gittask/commands/track.py
gittask/tui/app.py
gittask/tui/css/styles.tcss
gittask/tui/screens/dashboard.py
gittask/tui/screens/log_view.py
gittask/tui/screens/progress.py
gittask/tui/screens/status.py
gittask/tui/screens/tag_selection.py
gittask/tui/screens/task_options.py
gittask/tui/screens/task_search.py
gittask/tui/widgets/task_card.py
gittask_cli-0.2.0.dist-info/METADATA
gittask_cli-0.2.0.dist-info/WHEEL
gittask_cli-0.2.0.dist-info/entry_points.txt
gittask_cli-0.2.0.dist-info/RECORD
