Metadata-Version: 2.4
Name: gittask-cli
Version: 0.2.0
Summary: Git-Asana CLI & Time Tracker
Requires-Python: >=3.10
Requires-Dist: asana>=5.0.0
Requires-Dist: gitpython>=3.1.0
Requires-Dist: keyring>=24.0.0
Requires-Dist: pygithub
Requires-Dist: python-dateutil>=2.8.2
Requires-Dist: questionary>=2.0.0
Requires-Dist: textual>=0.40.0
Requires-Dist: thefuzz>=0.20.0
Requires-Dist: tinydb>=4.8.0
Requires-Dist: typer[all]>=0.9.0
Provides-Extra: dev
Requires-Dist: pytest; extra == 'dev'
Requires-Dist: pytest-asyncio; extra == 'dev'
Requires-Dist: pytest-mock; extra == 'dev'
